rdsparamsync/__init__.py
rdsparamsync/__main__.py
rdsparamsync/main.py
pg_rds_params_sync-0.2a2.dist-info/METADATA
pg_rds_params_sync-0.2a2.dist-info/WHEEL
pg_rds_params_sync-0.2a2.dist-info/entry_points.txt
pg_rds_params_sync-0.2a2.dist-info/top_level.txt
pg_rds_params_sync-0.2a2.dist-info/RECORD
