Metadata-Version: 2.1
Name: pg-rds-params-sync
Version: 0.2a2
Summary: Audit RDS PostgreSQL parameters for drift and compliance.
Home-page: https://github.com/levkk/pg-rds-params-sync
Author: Lev Kokotov
Author-email: lev.kokotov@instacart.com
License: UNKNOWN
Platform: UNKNOWN
Classifier: Programming Language :: Python :: 3
Classifier: License :: OSI Approved :: MIT License
Classifier: Operating System :: OS Independent
Requires-Python: >=3
Requires-Dist: Click (>=7.0)
Requires-Dist: colorama (>=0.4.3)
Requires-Dist: prettytable (>=0.7.2)
Requires-Dist: psycopg2 (>=2.8.4)
Requires-Dist: diskcache (>=4.1.0)
Requires-Dist: boto3 (>=1.11.9)
Requires-Dist: tqdm (>=4.46.0)
Provides-Extra: dev
Requires-Dist: pytest ; extra == 'dev'
